{"components_six-badge.md":"DaJCzY9d","changelog.md":"C6bTLS3e","components_six-checkbox.md":"DyUxGGDA","readme.md":"IBMym9tL","components_six-card.md":"BaGR1y8U","components_six-error-page.md":"DCDVaCcP","components_six-dropdown.md":"Dr6ihimm","guide_vue.md":"DbOgfzL6","components_six-button.md":"43TgAByl","components_six-dialog.md":"COkgGmk4","components_six-footer.md":"aQ56ttGB","components_six-file-list-item.md":"VCeGlSEa","components_six-avatar.md":"B0tZdIRq","components_six-language-switcher.md":"Ci024PaT","components_six-datepicker.md":"DteL1Cjb","components_six-alert.md":"7g_GVVsb","components_six-drawer.md":"C6sjBIVY","components_six-group-label.md":"DlFSCNbi","components_six-details.md":"CdKcl994","components_six-error.md":"DKtV-p_u","components_six-icon.md":"BbQ-1LJh","components_six-file-list.md":"LEUB8NVc","components_six-file-upload.md":"DeEBB42N","components_six-menu-item.md":"dYg8cmxd","components_six-menu-divider.md":"ndTSYKXi","components_six-icon-button.md":"a8kUHSex","components_six-layout-grid.md":"Bu5o1VjX","components_six-item-picker.md":"C63TiRyP","components_six-input.md":"BVCdn95-","components_six-menu.md":"BI8TbVOh","components_six-menu-label.md":"DVNHF4b5","components_six-progress-bar.md":"D8_O29o1","components_six-picto.md":"BLIZsyzV","components_six-progress-ring.md":"DKyLMjQW","components_six-radio.md":"B0GBMAUC","components_six-range.md":"CKJrOOFx","components_six-root.md":"DhOA1Izj","components_six-search-field.md":"-E4ErVLr","components_six-sidebar-item-group.md":"BosPPC1I","components_six-sidebar.md":"Df9mHOi4","components_six-sidebar-item.md":"CQUkv4IM","components_six-stage-indicator.md":"Yya84bwd","components_six-switch.md":"DY1gvIo5","components_six-spinner.md":"wAnDT3zH","components_six-tab-panel.md":"C5ziSDVK","components_six-select.md":"kOmIcOKR","components_six-tag.md":"D-FFOgHL","components_six-tab-group.md":"o0b4JTST","components_six-tab.md":"DXqpdHTb","components_six-main-container.md":"26rivN8x","components_six-header.md":"BDu1o8Fx","components_six-tile.md":"BgZ0sJ7J","guide_architecture.md":"DCUzWNY4","guide_design.md":"l92aqTRF","components_six-tooltip.md":"uxUrSrvr","components_six-timepicker.md":"Dda5Vcz4","index.md":"KrNvGkaa","guide_styling_tailwind.md":"DyyOmfDn","guide_angular.md":"D3EoCj9q","guide_styling_styles.md":"Cjo59YeJ","guide_readme.md":"B_RookEu","guide_styling_colors.md":"Cvg_PFbM","guide_styling_tables.md":"D02Bcojn","components_six-textarea.md":"BqxeXIEp","guide_upgrade-v4.md":"CTM8FO5G","guide_react.md":"DHU0pqJs"}
